x23408359/__init__.py
x23408359/calculations.py
x23408359-0.0.2.dist-info/licenses/LICENSE
x23408359-0.0.2.dist-info/METADATA
x23408359-0.0.2.dist-info/WHEEL
x23408359-0.0.2.dist-info/top_level.txt
x23408359-0.0.2.dist-info/RECORD
