Metadata-Version: 2.4
Name: x23408359
Version: 0.0.2
Summary: carbon emission and absorption caluclator
Home-page: https://github.com/pypa/sampleproject
Author: aftab_ahmed
Author-email: aftabkhna41.ak92@gmail.com
Classifier: Programming Language :: Python :: 3
Classifier: License :: OSI Approved :: MIT License
Classifier: Operating System :: OS Independent
Requires-Python: >=3.6
License-File: LICENSE
Dynamic: author
Dynamic: author-email
Dynamic: classifier
Dynamic: description-content-type
Dynamic: home-page
Dynamic: license-file
Dynamic: requires-python
Dynamic: summary
